odoo/addons/account_mass_reconcile_by_mrp_production/README.rst
odoo/addons/account_mass_reconcile_by_mrp_production/__init__.py
odoo/addons/account_mass_reconcile_by_mrp_production/__manifest__.py
odoo/addons/account_mass_reconcile_by_mrp_production/i18n/account_mass_reconcile_by_mrp_production.pot
odoo/addons/account_mass_reconcile_by_mrp_production/i18n/es.po
odoo/addons/account_mass_reconcile_by_mrp_production/i18n/sv.po
odoo/addons/account_mass_reconcile_by_mrp_production/models/__init__.py
odoo/addons/account_mass_reconcile_by_mrp_production/models/advanced_reconciliation.py
odoo/addons/account_mass_reconcile_by_mrp_production/models/base_advanced_reconciliation.py
odoo/addons/account_mass_reconcile_by_mrp_production/models/mass_reconcile.py
odoo/addons/account_mass_reconcile_by_mrp_production/readme/CONTRIBUTORS.rst
odoo/addons/account_mass_reconcile_by_mrp_production/readme/DESCRIPTION.rst
odoo/addons/account_mass_reconcile_by_mrp_production/readme/USAGE.rst
odoo/addons/account_mass_reconcile_by_mrp_production/security/ir.model.access.csv
odoo/addons/account_mass_reconcile_by_mrp_production/static/description/icon.png
odoo/addons/account_mass_reconcile_by_mrp_production/static/description/index.html
odoo/addons/account_mass_reconcile_by_mrp_production/views/mass_reconcile.xml
odoo14_addon_account_mass_reconcile_by_mrp_production-14.0.1.0.1.dev7.dist-info/METADATA
odoo14_addon_account_mass_reconcile_by_mrp_production-14.0.1.0.1.dev7.dist-info/WHEEL
odoo14_addon_account_mass_reconcile_by_mrp_production-14.0.1.0.1.dev7.dist-info/top_level.txt
odoo14_addon_account_mass_reconcile_by_mrp_production-14.0.1.0.1.dev7.dist-info/RECORD
