Metadata-Version: 2.1
Name: odoo14-addon-account-mass-reconcile-by-mrp-production
Version: 14.0.1.0.1.dev7
Summary: Allows to reconcile based on the MO line
Home-page: https://github.com/OCA/account-reconcile
Author: ForgeFlow S.L., Odoo Community Association (OCA)
Author-email: support@odoo-community.org
License: AGPL-3
Platform: UNKNOWN
Classifier: Programming Language :: Python
Classifier: Framework :: Odoo
Classifier: Framework :: Odoo :: 14.0
Classifier: License :: OSI Approved :: GNU Affero General Public License v3
Requires-Python: >=3.6
Requires-Dist: odoo14-addon-account-mass-reconcile
Requires-Dist: odoo14-addon-account-move-line-mrp-info
Requires-Dist: odoo <14.1dev,>=14.0a
